{"1":{"isFlagged":false,"answeredIndex":3,"isCorrect":true},"2":{"isFlagged":false,"answeredIndex":3,"isCorrect":true},"3":{"isFlagged":false,"answeredIndex":1,"isCorrect":true},"4":{"isFlagged":false,"answeredIndex":0,"isCorrect":true},"5":{"isFlagged":false,"answeredIndex":1,"isCorrect":true},"6":{"isFlagged":false,"answeredIndex":1,"isCorrect":true},"7":{"isFlagged":false,"answeredIndex":3,"isCorrect":true},"8":{"isFlagged":false,"answeredIndex":0,"isCorrect":true},"9":{"isFlagged":false,"answeredIndex":3,"isCorrect":false},"10":{"isFlagged":false,"answeredIndex":3,"isCorrect":true},"11":{"isFlagged":false,"answeredIndex":3,"isCorrect":true},"12":{"isFlagged":false,"answeredIndex":0,"isCorrect":true},"13":{"isFlagged":false,"answeredIndex":1,"isCorrect":true},"14":{"isFlagged":false,"answeredIndex":0,"isCorrect":true},"15":{"isFlagged":false,"answeredIndex":3,"isCorrect":true},"16":{"isFlagged":false,"answeredIndex":3,"isCorrect":true},"17":{"isFlagged":false,"answeredIndex":1,"isCorrect":true},"18":{"isFlagged":false,"answeredIndex":3,"isCorrect":true},"19":{"isFlagged":false,"answeredIndex":3,"isCorrect":true},"20":{"isFlagged":false,"answeredIndex":2,"isCorrect":true},"21":{"isFlagged":false,"answeredIndex":2,"isCorrect":true},"22":{"isFlagged":false,"answeredIndex":3,"isCorrect":true},"23":{"isFlagged":false,"answeredIndex":3,"isCorrect":true},"24":{"isFlagged":false,"answeredIndex":3,"isCorrect":true},"25":{"isFlagged":false,"answeredIndex":0,"isCorrect":true},"26":{"isFlagged":false,"answeredIndex":3,"isCorrect":true},"27":{"isFlagged":false,"answeredIndex":1,"isCorrect":true},"28":{"isFlagged":false,"answeredIndex":3,"isCorrect":true},"29":{"isFlagged":false,"answeredIndex":2,"isCorrect":true},"30":{"isFlagged":false,"answeredIndex":3,"isCorrect":true},"31":{"isFlagged":false,"answeredIndex":2,"isCorrect":true},"32":{"isFlagged":false,"answeredIndex":1,"isCorrect":false},"33":{"isFlagged":false,"answeredIndex":0,"isCorrect":true},"34":{"isFlagged":false,"answeredIndex":1,"isCorrect":true},"35":{"isFlagged":false,"answeredIndex":2,"isCorrect":true},"36":{"isFlagged":false,"answeredIndex":2,"isCorrect":true},"37":{"isFlagged":false,"answeredIndex":3,"isCorrect":true},"38":{"isFlagged":false,"answeredIndex":1,"isCorrect":true},"39":{"isFlagged":false,"answeredIndex":1,"isCorrect":false},"40":{"isFlagged":false,"answeredIndex":0,"isCorrect":true},"41":{"isFlagged":false,"answeredIndex":2,"isCorrect":true},"42":{"isFlagged":false,"answeredIndex":2,"isCorrect":true},"43":{"isFlagged":false,"answeredIndex":3,"isCorrect":true},"44":{"isFlagged":false,"answeredIndex":3,"isCorrect":true},"45":{"isFlagged":false,"answeredIndex":1,"isCorrect":true},"46":{"isFlagged":false,"answeredIndex":2,"isCorrect":true},"47":{"isFlagged":false,"answeredIndex":3,"isCorrect":true},"48":{"isFlagged":false,"answeredIndex":1,"isCorrect":true},"49":{"isFlagged":false,"answeredIndex":3,"isCorrect":true},"50":{"isFlagged":false,"answeredIndex":2,"isCorrect":true},"51":{"isFlagged":false,"answeredIndex":1,"isCorrect":true},"52":{"isFlagged":false,"answeredIndex":2,"isCorrect":true},"53":{"isFlagged":false,"answeredIndex":3,"isCorrect":true},"54":{"isFlagged":false,"answeredIndex":2,"isCorrect":true},"55":{"isFlagged":false,"answeredIndex":2,"isCorrect":true},"56":{"isFlagged":false,"answeredIndex":2,"isCorrect":true},"57":{"isFlagged":false,"answeredIndex":2,"isCorrect":true},"58":{"isFlagged":false,"answeredIndex":2,"isCorrect":true},"59":{"isFlagged":false,"answeredIndex":1,"isCorrect":true},"60":{"isFlagged":false,"answeredIndex":0,"isCorrect":false},"61":{"isFlagged":false,"answeredIndex":3,"isCorrect":true},"62":{"isFlagged":false,"answeredIndex":2,"isCorrect":true},"63":{"isFlagged":false,"answeredIndex":3,"isCorrect":true},"64":{"isFlagged":false,"answeredIndex":0,"isCorrect":true},"65":{"isFlagged":false,"answeredIndex":2,"isCorrect":true},"66":{"isFlagged":false,"answeredIndex":3,"isCorrect":true},"67":{"isFlagged":false,"answeredIndex":0,"isCorrect":true},"68":{"isFlagged":false,"answeredIndex":3,"isCorrect":true},"69":{"isFlagged":false,"answeredIndex":3,"isCorrect":true},"70":{"isFlagged":false,"answeredIndex":2,"isCorrect":true},"71":{"isFlagged":false,"answeredIndex":0,"isCorrect":true},"72":{"isFlagged":false,"answeredIndex":0,"isCorrect":true},"73":{"isFlagged":false,"answeredIndex":0,"isCorrect":true},"74":{"isFlagged":false,"answeredIndex":0,"isCorrect":true},"75":{"isFlagged":false,"answeredIndex":3,"isCorrect":false},"76":{"isFlagged":false,"answeredIndex":2,"isCorrect":true},"77":{"isFlagged":false,"answeredIndex":0,"isCorrect":true},"78":{"isFlagged":false,"answeredIndex":1,"isCorrect":true},"79":{"isFlagged":false,"answeredIndex":0,"isCorrect":true},"80":{"isFlagged":false,"answeredIndex":0,"isCorrect":true},"81":{"isFlagged":true,"answeredIndex":3,"isCorrect":true},"82":{"isFlagged":false,"answeredIndex":2,"isCorrect":true},"83":{"isFlagged":false,"answeredIndex":0,"isCorrect":true},"84":{"isFlagged":false,"answeredIndex":1,"isCorrect":true},"85":{"isFlagged":false,"answeredIndex":0,"isCorrect":true},"86":{"isFlagged":true,"answeredIndex":3,"isCorrect":true},"87":{"isFlagged":false,"answeredIndex":2,"isCorrect":true},"88":{"isFlagged":false,"answeredIndex":2,"isCorrect":true},"89":{"isFlagged":false,"answeredIndex":2,"isCorrect":true},"90":{"isFlagged":false,"answeredIndex":3,"isCorrect":true},"91":{"isFlagged":false,"answeredIndex":0,"isCorrect":false},"92":{"isFlagged":false,"answeredIndex":2,"isCorrect":true},"93":{"isFlagged":false,"answeredIndex":3,"isCorrect":true},"94":{"isFlagged":false,"answeredIndex":3,"isCorrect":true},"95":{"isFlagged":false,"answeredIndex":1,"isCorrect":true},"96":{"isFlagged":false,"answeredIndex":3,"isCorrect":true},"97":{"isFlagged":false,"answeredIndex":3,"isCorrect":true},"98":{"isFlagged":false,"answeredIndex":0,"isCorrect":true},"99":{"isFlagged":false,"answeredIndex":1,"isCorrect":true},"100":{"isFlagged":false,"answeredIndex":3,"isCorrect":true},"101":{"isFlagged":false,"answeredIndex":0,"isCorrect":true},"102":{"isFlagged":false,"answeredIndex":3,"isCorrect":true},"103":{"isFlagged":false,"answeredIndex":1,"isCorrect":false},"104":{"isFlagged":false,"answeredIndex":1,"isCorrect":true},"105":{"isFlagged":false,"answeredIndex":3,"isCorrect":false},"106":{"isFlagged":false,"answeredIndex":0,"isCorrect":true},"107":{"isFlagged":false,"answeredIndex":0,"isCorrect":false},"108":{"isFlagged":false,"answeredIndex":0,"isCorrect":true},"109":{"isFlagged":false,"answeredIndex":0,"isCorrect":true},"110":{"isFlagged":false,"answeredIndex":3,"isCorrect":true},"111":{"isFlagged":false,"answeredIndex":1,"isCorrect":false},"112":{"isFlagged":false,"answeredIndex":2,"isCorrect":false},"113":{"isFlagged":false,"answeredIndex":0,"isCorrect":false},"114":{"isFlagged":false,"answeredIndex":0,"isCorrect":true},"115":{"isFlagged":false,"answeredIndex":2,"isCorrect":true},"116":{"isFlagged":false,"answeredIndex":3,"isCorrect":false},"117":{"isFlagged":false,"answeredIndex":0,"isCorrect":true},"118":{"isFlagged":false,"answeredIndex":0,"isCorrect":false},"119":{"isFlagged":false,"answeredIndex":0,"isCorrect":true},"120":{"isFlagged":false,"answeredIndex":2,"isCorrect":false},"121":{"isFlagged":false,"answeredIndex":3,"isCorrect":true},"122":{"isFlagged":false,"answeredIndex":1,"isCorrect":true},"123":{"isFlagged":false,"answeredIndex":2,"isCorrect":true},"124":{"isFlagged":false,"answeredIndex":1,"isCorrect":true},"125":{"isFlagged":false,"answeredIndex":0,"isCorrect":true},"126":{"isFlagged":false,"answeredIndex":1,"isCorrect":false},"127":{"isFlagged":false,"answeredIndex":2,"isCorrect":false},"128":{"isFlagged":false,"answeredIndex":3,"isCorrect":true},"129":{"isFlagged":false,"answeredIndex":1,"isCorrect":false},"130":{"isFlagged":false,"answeredIndex":2,"isCorrect":false},"131":{"isFlagged":false,"answeredIndex":0,"isCorrect":true},"132":{"isFlagged":false,"answeredIndex":1,"isCorrect":false},"133":{"isFlagged":false,"answeredIndex":3,"isCorrect":false},"134":{"isFlagged":false,"answeredIndex":1,"isCorrect":false},"135":{"isFlagged":false,"answeredIndex":1,"isCorrect":false},"136":{"isFlagged":false,"answeredIndex":2,"isCorrect":false},"137":{"isFlagged":false,"answeredIndex":2,"isCorrect":true},"138":{"isFlagged":false,"answeredIndex":0,"isCorrect":false},"139":{"isFlagged":false,"answeredIndex":1,"isCorrect":true},"140":{"isFlagged":false,"answeredIndex":1,"isCorrect":true},"141":{"isFlagged":false,"answeredIndex":0,"isCorrect":true},"142":{"isFlagged":false,"answeredIndex":3,"isCorrect":true},"143":{"isFlagged":false,"answeredIndex":1,"isCorrect":true},"144":{"isFlagged":false,"answeredIndex":1,"isCorrect":false},"145":{"isFlagged":false,"answeredIndex":0,"isCorrect":false},"146":{"isFlagged":false,"answeredIndex":1,"isCorrect":true},"147":{"isFlagged":false,"answeredIndex":0,"isCorrect":true},"148":{"isFlagged":false,"answeredIndex":2,"isCorrect":true},"149":{"isFlagged":false,"answeredIndex":0,"isCorrect":true},"150":{"isFlagged":false,"answeredIndex":2,"isCorrect":true},"151":{"isFlagged":false,"answeredIndex":1,"isCorrect":false},"152":{"isFlagged":false,"answeredIndex":2,"isCorrect":true},"153":{"isFlagged":false,"answeredIndex":3,"isCorrect":true},"154":{"isFlagged":false,"answeredIndex":0,"isCorrect":true},"155":{"isFlagged":false,"answeredIndex":1,"isCorrect":true},"156":{"isFlagged":false,"answeredIndex":1,"isCorrect":true},"157":{"isFlagged":false,"answeredIndex":0,"isCorrect":true},"158":{"isFlagged":false,"answeredIndex":1,"isCorrect":false},"159":{"isFlagged":false,"answeredIndex":0,"isCorrect":false},"160":{"isFlagged":false,"answeredIndex":2,"isCorrect":false},"161":{"isFlagged":false,"answeredIndex":1,"isCorrect":true},"162":{"isFlagged":false,"answeredIndex":2,"isCorrect":true},"163":{"isFlagged":false,"answeredIndex":3,"isCorrect":true},"164":{"isFlagged":false,"answeredIndex":1,"isCorrect":false},"165":{"isFlagged":false,"answeredIndex":0,"isCorrect":true},"166":{"isFlagged":false,"answeredIndex":3,"isCorrect":false},"167":{"isFlagged":false,"answeredIndex":3,"isCorrect":false},"168":{"isFlagged":false,"answeredIndex":0,"isCorrect":false},"169":{"isFlagged":false,"answeredIndex":3,"isCorrect":true},"170":{"isFlagged":false,"answeredIndex":1,"isCorrect":true},"171":{"isFlagged":false,"answeredIndex":3,"isCorrect":false},"172":{"isFlagged":false,"answeredIndex":3,"isCorrect":false},"173":{"isFlagged":false,"answeredIndex":0,"isCorrect":false},"174":{"isFlagged":false,"answeredIndex":0,"isCorrect":false},"175":{"isFlagged":false,"answeredIndex":3,"isCorrect":true},"176":{"isFlagged":false,"answeredIndex":2,"isCorrect":true},"177":{"isFlagged":false,"answeredIndex":1,"isCorrect":true},"178":{"isFlagged":false,"answeredIndex":3,"isCorrect":false},"179":{"isFlagged":false,"answeredIndex":2,"isCorrect":true},"180":{"isFlagged":false,"answeredIndex":0,"isCorrect":false},"181":{"isFlagged":false,"answeredIndex":2,"isCorrect":true},"182":{"isFlagged":false,"answeredIndex":3,"isCorrect":true},"183":{"isFlagged":false,"answeredIndex":1,"isCorrect":false},"184":{"isFlagged":false,"answeredIndex":1,"isCorrect":false},"185":{"isFlagged":false,"answeredIndex":3,"isCorrect":false},"186":{"isFlagged":false,"answeredIndex":3,"isCorrect":false},"187":{"isFlagged":false,"answeredIndex":0,"isCorrect":true},"188":{"isFlagged":false,"answeredIndex":0,"isCorrect":true},"189":{"isFlagged":false,"answeredIndex":0,"isCorrect":true},"190":{"isFlagged":false,"answeredIndex":1,"isCorrect":false},"191":{"isFlagged":false,"answeredIndex":3,"isCorrect":true},"192":{"isFlagged":false,"answeredIndex":1,"isCorrect":true},"193":{"isFlagged":false,"answeredIndex":1,"isCorrect":true},"194":{"isFlagged":false,"answeredIndex":1,"isCorrect":false},"195":{"isFlagged":false,"answeredIndex":3,"isCorrect":true},"196":{"isFlagged":false,"answeredIndex":2,"isCorrect":false},"197":{"isFlagged":false,"answeredIndex":2,"isCorrect":false},"198":{"isFlagged":false,"answeredIndex":1,"isCorrect":false},"199":{"isFlagged":false,"answeredIndex":3,"isCorrect":false},"200":{"isFlagged":false,"answeredIndex":3,"isCorrect":true},"201":{"isFlagged":false,"answeredIndex":2,"isCorrect":false},"202":{"isFlagged":false,"answeredIndex":2,"isCorrect":true},"203":{"isFlagged":false,"answeredIndex":1,"isCorrect":false},"204":{"isFlagged":false,"answeredIndex":3,"isCorrect":true},"205":{"isFlagged":false,"answeredIndex":3,"isCorrect":false},"206":{"isFlagged":false,"answeredIndex":0,"isCorrect":true},"207":{"isFlagged":false,"answeredIndex":0,"isCorrect":false},"208":{"isFlagged":false,"answeredIndex":2,"isCorrect":false},"209":{"isFlagged":false,"answeredIndex":2,"isCorrect":false},"210":{"isFlagged":false,"answeredIndex":1,"isCorrect":true},"211":{"isFlagged":false,"answeredIndex":2,"isCorrect":false},"212":{"isFlagged":false,"answeredIndex":0,"isCorrect":false},"213":{"isFlagged":false,"answeredIndex":0,"isCorrect":true},"214":{"isFlagged":false,"answeredIndex":3,"isCorrect":true},"215":{"isFlagged":false,"answeredIndex":3,"isCorrect":false},"216":{"isFlagged":false,"answeredIndex":3,"isCorrect":true},"217":{"isFlagged":false,"answeredIndex":1,"isCorrect":true},"218":{"isFlagged":false,"answeredIndex":2,"isCorrect":true},"219":{"isFlagged":false,"answeredIndex":3,"isCorrect":true},"220":{"isFlagged":false,"answeredIndex":2,"isCorrect":true},"221":{"isFlagged":false,"answeredIndex":2,"isCorrect":true},"222":{"isFlagged":false,"answeredIndex":0,"isCorrect":true},"223":{"isFlagged":false,"answeredIndex":1,"isCorrect":true},"224":{"isFlagged":false,"answeredIndex":2,"isCorrect":true},"225":{"isFlagged":false,"answeredIndex":1,"isCorrect":true},"226":{"isFlagged":false,"answeredIndex":2,"isCorrect":true},"227":{"isFlagged":false,"answeredIndex":2,"isCorrect":true},"228":{"isFlagged":false,"answeredIndex":1,"isCorrect":true},"229":{"isFlagged":false,"answeredIndex":1,"isCorrect":true},"230":{"isFlagged":false,"answeredIndex":0,"isCorrect":true},"231":{"isFlagged":false,"answeredIndex":0,"isCorrect":true},"232":{"isFlagged":false,"answeredIndex":0,"isCorrect":false},"233":{"isFlagged":false,"answeredIndex":2,"isCorrect":true},"234":{"isFlagged":false,"answeredIndex":2,"isCorrect":true},"235":{"isFlagged":false,"answeredIndex":3,"isCorrect":true},"236":{"isFlagged":false,"answeredIndex":1,"isCorrect":false},"237":{"isFlagged":false,"answeredIndex":2,"isCorrect":true},"238":{"isFlagged":false,"answeredIndex":2,"isCorrect":true},"239":{"isFlagged":false,"answeredIndex":3,"isCorrect":true},"240":{"isFlagged":false,"answeredIndex":3,"isCorrect":true},"241":{"isFlagged":false,"answeredIndex":3,"isCorrect":false},"242":{"isFlagged":false,"answeredIndex":3,"isCorrect":true},"243":{"isFlagged":false,"answeredIndex":3,"isCorrect":true},"244":{"isFlagged":false,"answeredIndex":1,"isCorrect":false},"245":{"isFlagged":false,"answeredIndex":2,"isCorrect":true},"246":{"isFlagged":false,"answeredIndex":2,"isCorrect":false},"247":{"isFlagged":false,"answeredIndex":2,"isCorrect":false},"248":{"isFlagged":false,"answeredIndex":2,"isCorrect":true},"249":{"isFlagged":false,"answeredIndex":0,"isCorrect":false},"250":{"isFlagged":false,"answeredIndex":2,"isCorrect":false},"251":{"isFlagged":false,"answeredIndex":2,"isCorrect":true},"252":{"isFlagged":false,"answeredIndex":2,"isCorrect":false},"253":{"isFlagged":false,"answeredIndex":1,"isCorrect":false},"254":{"isFlagged":false,"answeredIndex":1,"isCorrect":false},"255":{"isFlagged":false,"answeredIndex":3,"isCorrect":true},"256":{"isFlagged":false,"answeredIndex":3,"isCorrect":true},"257":{"isFlagged":false,"answeredIndex":0,"isCorrect":true},"258":{"isFlagged":false,"answeredIndex":0,"isCorrect":false},"259":{"isFlagged":false,"answeredIndex":0,"isCorrect":true},"260":{"isFlagged":false,"answeredIndex":3,"isCorrect":true},"261":{"isFlagged":false,"answeredIndex":3,"isCorrect":true},"262":{"isFlagged":false,"answeredIndex":2,"isCorrect":true},"263":{"isFlagged":false,"answeredIndex":1,"isCorrect":true},"264":{"isFlagged":false,"answeredIndex":2,"isCorrect":true},"265":{"isFlagged":false,"answeredIndex":3,"isCorrect":false},"266":{"isFlagged":false,"answeredIndex":2,"isCorrect":false},"267":{"isFlagged":false,"answeredIndex":3,"isCorrect":true},"268":{"isFlagged":false,"answeredIndex":3,"isCorrect":true},"269":{"isFlagged":false,"answeredIndex":0,"isCorrect":true},"270":{"isFlagged":false,"answeredIndex":3,"isCorrect":true},"271":{"isFlagged":false,"answeredIndex":0,"isCorrect":true},"272":{"isFlagged":false,"answeredIndex":3,"isCorrect":true},"273":{"isFlagged":false,"answeredIndex":0,"isCorrect":false},"274":{"isFlagged":false,"answeredIndex":2,"isCorrect":true},"275":{"isFlagged":false,"answeredIndex":1,"isCorrect":true},"276":{"isFlagged":false,"answeredIndex":3,"isCorrect":true},"277":{"isFlagged":false,"answeredIndex":1,"isCorrect":false},"278":{"isFlagged":false,"answeredIndex":0,"isCorrect":false},"279":{"isFlagged":false,"answeredIndex":2,"isCorrect":true},"280":{"isFlagged":false,"answeredIndex":1,"isCorrect":true},"281":{"isFlagged":false,"answeredIndex":3,"isCorrect":false},"282":{"isFlagged":false,"answeredIndex":0,"isCorrect":false},"283":{"isFlagged":false,"answeredIndex":2,"isCorrect":true},"284":{"isFlagged":false,"answeredIndex":1,"isCorrect":false},"285":{"isFlagged":false,"answeredIndex":3,"isCorrect":false},"286":{"isFlagged":false,"answeredIndex":0,"isCorrect":true},"287":{"isFlagged":false,"answeredIndex":3,"isCorrect":false},"288":{"isFlagged":false,"answeredIndex":1,"isCorrect":false},"289":{"isFlagged":false,"answeredIndex":0,"isCorrect":true},"290":{"isFlagged":false,"answeredIndex":0,"isCorrect":true},"291":{"isFlagged":false,"answeredIndex":0,"isCorrect":false},"292":{"isFlagged":false,"answeredIndex":1,"isCorrect":false},"293":{"isFlagged":false,"answeredIndex":3,"isCorrect":false},"294":{"isFlagged":false,"answeredIndex":0,"isCorrect":true},"295":{"isFlagged":false,"answeredIndex":3,"isCorrect":true},"296":{"isFlagged":false,"answeredIndex":1,"isCorrect":true},"297":{"isFlagged":false,"answeredIndex":3,"isCorrect":true},"298":{"isFlagged":false,"answeredIndex":1,"isCorrect":false},"299":{"isFlagged":false,"answeredIndex":0,"isCorrect":false},"300":{"isFlagged":false,"answeredIndex":3,"isCorrect":false},"301":{"isFlagged":false,"answeredIndex":3,"isCorrect":true},"302":{"isFlagged":false,"answeredIndex":2,"isCorrect":false},"303":{"isFlagged":false,"answeredIndex":1,"isCorrect":false},"304":{"isFlagged":false,"answeredIndex":1,"isCorrect":false},"305":{"isFlagged":false,"answeredIndex":0,"isCorrect":true},"306":{"isFlagged":false,"answeredIndex":2,"isCorrect":true},"307":{"isFlagged":false,"answeredIndex":3,"isCorrect":true},"308":{"isFlagged":false,"answeredIndex":0,"isCorrect":true},"309":{"isFlagged":false,"answeredIndex":3,"isCorrect":false},"310":{"isFlagged":false,"answeredIndex":0,"isCorrect":false},"311":{"isFlagged":false,"answeredIndex":0,"isCorrect":true},"312":{"isFlagged":false,"answeredIndex":2,"isCorrect":false},"313":{"isFlagged":false,"answeredIndex":0,"isCorrect":false},"314":{"isFlagged":false,"answeredIndex":0,"isCorrect":false},"315":{"isFlagged":false,"answeredIndex":3,"isCorrect":true},"316":{"isFlagged":false,"answeredIndex":3,"isCorrect":true},"317":{"isFlagged":false,"answeredIndex":3,"isCorrect":true},"318":{"isFlagged":false,"answeredIndex":3,"isCorrect":true},"319":{"isFlagged":false,"answeredIndex":3,"isCorrect":true},"320":{"isFlagged":false,"answeredIndex":3,"isCorrect":true},"321":{"isFlagged":false,"answeredIndex":0,"isCorrect":false},"322":{"isFlagged":false,"answeredIndex":3,"isCorrect":false},"323":{"isFlagged":false,"answeredIndex":0,"isCorrect":true},"324":{"isFlagged":false,"answeredIndex":0,"isCorrect":true},"325":{"isFlagged":false,"answeredIndex":3,"isCorrect":true},"326":{"isFlagged":false,"answeredIndex":3,"isCorrect":true},"327":{"isFlagged":false,"answeredIndex":0,"isCorrect":true},"328":{"isFlagged":false,"answeredIndex":2,"isCorrect":true},"329":{"isFlagged":false,"answeredIndex":2,"isCorrect":true},"330":{"isFlagged":false,"answeredIndex":3,"isCorrect":true},"331":{"isFlagged":false,"answeredIndex":3,"isCorrect":true},"332":{"isFlagged":false,"answeredIndex":3,"isCorrect":false},"333":{"isFlagged":false,"answeredIndex":0,"isCorrect":true},"334":{"isFlagged":false,"answeredIndex":2,"isCorrect":true},"335":{"isFlagged":false,"answeredIndex":0,"isCorrect":true},"336":{"isFlagged":false,"answeredIndex":0,"isCorrect":true},"337":{"isFlagged":false,"answeredIndex":2,"isCorrect":true},"338":{"isFlagged":false,"answeredIndex":0,"isCorrect":false},"339":{"isFlagged":false,"answeredIndex":1,"isCorrect":true},"340":{"isFlagged":false,"answeredIndex":3,"isCorrect":false},"341":{"isFlagged":false,"answeredIndex":0,"isCorrect":false},"342":{"isFlagged":false,"answeredIndex":0,"isCorrect":true},"343":{"isFlagged":false,"answeredIndex":0,"isCorrect":true},"344":{"isFlagged":false,"answeredIndex":3,"isCorrect":false},"345":{"isFlagged":false,"answeredIndex":2,"isCorrect":false},"346":{"isFlagged":false,"answeredIndex":1,"isCorrect":true},"347":{"isFlagged":false,"answeredIndex":0,"isCorrect":false},"348":{"isFlagged":false,"answeredIndex":0,"isCorrect":true},"349":{"isFlagged":false,"answeredIndex":1,"isCorrect":false},"350":{"isFlagged":false,"answeredIndex":2,"isCorrect":true}}